winzy_head_tail/__init__.py
winzy_head_tail/head.py
winzy_head_tail/tail.py
winzy_head_tail-0.0.1.dist-info/LICENSE
winzy_head_tail-0.0.1.dist-info/METADATA
winzy_head_tail-0.0.1.dist-info/WHEEL
winzy_head_tail-0.0.1.dist-info/entry_points.txt
winzy_head_tail-0.0.1.dist-info/top_level.txt
winzy_head_tail-0.0.1.dist-info/RECORD
