Metadata-Version: 2.1
Name: winzy-head-tail
Version: 0.0.1
Summary: Mimics head and tail command using python
Author: Sukhbinder Singh
License: Apache-2.0
Project-URL: Homepage, https://github.com/sukhbinder/winzy-head-tail
Project-URL: Changelog, https://github.com/sukhbinder/winzy-head-tail/releases
Project-URL: Issues, https://github.com/sukhbinder/winzy-head-tail/issues
Project-URL: CI, https://github.com/sukhbinder/winzy-head-tail/actions
Classifier: License :: OSI Approved :: Apache Software License
License-File: LICENSE
Requires-Dist: winzy
Provides-Extra: test
Requires-Dist: pytest; extra == "test"
